future_sales/__init__.py
future_sales/data/build_features.py
future_sales/data/etl.py
future_sales/data/utils.py
future_sales/predict.py
future_sales/train.py
future_sales/utils.py
future_sales-0.1.1.dist-info/entry_points.txt
future_sales-0.1.1.dist-info/WHEEL
future_sales-0.1.1.dist-info/METADATA
future_sales-0.1.1.dist-info/RECORD
