Metadata-Version: 2.1
Name: future-sales
Version: 0.1.1
Summary: 
Author: Sabina Bayramova
Author-email: sb.sabina00@gmail.com
Requires-Python: >=3.9,<4.0
Classifier: Programming Language :: Python :: 3
Classifier: Programming Language :: Python :: 3.10
Classifier: Programming Language :: Python :: 3.9
Requires-Dist: category-encoders (>=2.5.1,<3.0.0)
Requires-Dist: click (>=8.1.3,<9.0.0)
Requires-Dist: hyperopt (>=0.2.7,<0.3.0)
Requires-Dist: pandas (>=1.5.2,<2.0.0)
Requires-Dist: scikit-learn (>=1.2.0,<2.0.0)
Requires-Dist: xgboost (>=1.7.2,<2.0.0)
